setup.py
common_stats_dists/Binomialdistribution.py
common_stats_dists/Gaussiandistribution.py
common_stats_dists/Generaldistribution.py
common_stats_dists/__init__.py
common_stats_dists.egg-info/PKG-INFO
common_stats_dists.egg-info/SOURCES.txt
common_stats_dists.egg-info/dependency_links.txt
common_stats_dists.egg-info/not-zip-safe
common_stats_dists.egg-info/top_level.txt