Metadata-Version: 2.1
Name: common-stats-dists
Version: 0.1
Summary: Gaussian and Binomial distributions
Home-page: UNKNOWN
Author: Yining Yuan
Author-email: yiningyuan322@gmail.com
License: UNKNOWN
Platform: UNKNOWN
